[
  {
    "name": "Harry Shen",
    "email": "hashen@nvisionglobal.com",
    "active": true
  },
  {
    "name": "Jesse Zhang",
    "email": "jesse.zhang@nvisionglobal.com",
    "active": false
  },
  {
    "name": "Cathy Xue",
    "email": "cxue@nvisionglobal.com",
    "active": true
  },
  {
    "name": "Sandra Zheng",
    "email": "szheng@nvisionglobal.com",
    "active": false
  },
  {
    "name": "Annice Xu",
    "email": "axu@nvisionglobal.com",
    "active": false
  },
  {
    "name": "Ada Hu",
    "email": "ahu@nvisionglobal.com",
    "active": true
  },
  {
    "name": "Bella Li",
    "email": "Bella.li@nvisionglobal.com",
    "active": false
  },
  {
    "name": "Mia Chen",
    "email": "mia.chen@nvisionglobal.com",
    "active": false
  },
  {
    "name": "FU SHEN",
    "email": "shenfu0124@163.com",
    "active": true
  },
  {
    "name": "Lucia Liu",
    "email": "lliu@nvisionglobal.com",
    "active": false
  },
  {
    "name": "Happiness Hang",
    "email": "happinesshang@qq.com",
    "active": false
  }
]